pybmc/__init__.py
pybmc/bmc.py
pybmc/data.py
pybmc/inference_utils.py
pybmc/sampling_utils.py
pybmc/selected_data.h5
pybmc/test.ipynb
pybmc-0.2.4.dist-info/METADATA
pybmc-0.2.4.dist-info/WHEEL
pybmc-0.2.4.dist-info/licenses/AUTHORS.md
pybmc-0.2.4.dist-info/licenses/LICENSE
pybmc-0.2.4.dist-info/RECORD
