Metadata-Version: 2.4
Name: pybmc
Version: 0.2.4
Summary: A package for Bayesian model combination
License: GPL-3.0
License-File: AUTHORS.md
License-File: LICENSE
Author: Kyle Godbey
Author-email: pybmc@ascsn.net
Requires-Python: >=3.11,<4.0
Classifier: License :: OSI Approved :: GNU General Public License v3 (GPLv3)
Classifier: Programming Language :: Python :: 3
Classifier: Programming Language :: Python :: 3.11
Classifier: Programming Language :: Python :: 3.12
Classifier: Programming Language :: Python :: 3.13
Classifier: Programming Language :: Python :: 3.14
Requires-Dist: matplotlib (>=3.7.0,<4.0.0)
Requires-Dist: numpy (>=2.0.0,<3.0.0)
Requires-Dist: pandas (>=2.0.0,<3.0.0)
Requires-Dist: scikit-learn (>=1.3.0,<2.0.0)
Requires-Dist: scipy (>=1.15.0,<2.0.0)
Requires-Dist: tables (>=3.10.2,<4.0.0)
Project-URL: Documentation, https://ascsn.github.io/pybmc/
Project-URL: Homepage, https://github.com/ascsn/pybmc
Project-URL: Repository, https://github.com/ascsn/pybmc
